Workbook

Sheet Raw Data
A1: Product_ID | B1: Product_Name | C1: Catagory | D1: Supplier_ID | E1: Supplier_Name | F1: Stock_Quantity | G1: Reorder_Level | H1: Reorder_Quantity | I1: Unit_Price | J1: Date_Received | K1: Last_Order_Date | L1: Expiration_Date | M1: Warehouse_Location | N1: Sales_Volume | O1: Inventory_Turnover_Rate | P1: Status
A2: 29-205-1132 | B2: Sushi Rice | C2: Grains & Pulses | D2: 38-037-1699 | E2: Jaxnation | F2: 22 | G2: 72 | H2: 70 | I2: ? 4.50 | J2: 45520 | K2: 45472 | L2: 45554 | M2: 48 Del Sol Trail | N2: 32 | O2: 19 | P2: Discontinued
A3: 40-681-9981 | B3: Arabica Coffee | C3: Beverages | D3: 54-470-2479 | E3: Feedmix | F3: 45 | G3: 77 | H3: 2 | I3: ? 20.00 | J3: 45597 | K3: 45441 | L3: 45420 | M3: 36 3rd Place | N3: 85 | O3: 1 | P3: Discontinued
A4: 06-955-3428 | B4: Black Rice | C4: Grains & Pulses | D4: 54-031-2945 | E4: Vinder | F4: 30 | G4: 38 | H4: 83 | I4: ? 6.00 | J4: 45507 | K4: 45453 | L4: 45557 | M4: 3296 Walton Court | N4: 31 | O4: 34 | P4: Backordered
A5: 71-594-6552 | B5: Long Grain Rice | C5: Grains & Pulses | D5: 63-492-7603 | E5: Brightbean | F5: 12 | G5: 59 | H5: 62 | I5: ? 1.50 | J5: 45634 | K5: 45707 | L5: 45399 | M5: 3 Westerfield Crossing | N5: 95 | O5: 99 | P5: Active
A6: 57-437-1828 | B6: Plum | C6: Fruits & Vegetables | D6: 54-226-4308 | E6: Topicstorm | F6: 37 | G6: 30 | H6: 74 | I6: ? 4.00 | J6: 45476 | K6: 45576 | L6: 45570 | M6: 15068 Scoville Court | N6: 62 | O6: 25 | P6: Backordered
A7: 21-120-6238 | B7: All-Purpose Flour | C7: Grains & Pulses | D7: 86-292-4587 | E7: Dabjam | F7: 55 | G7: 33 | H7: 14 | I7: ? 1.75 | J7: 45629 | K7: 45438 | L7: 45540 | M7: 050 Mcbride Avenue | N7: 34 | O7: 62 | P7: Discontinued
A8: 71-516-1996 | B8: Corn Oil | C8: Oils & Fats | D8: 04-391-7610 | E8: Tagfeed | F8: 96 | G8: 52 | H8: 16 | I8: ? 2.50 | J8: 45369 | K8: 45419 | L8: 45463 | M8: 12 Truax Court | N8: 67 | O8: 13 | P8: Active
A9: 39-629-5554 | B9: Egg (Goose) | C9: Dairy | D9: 67-679-4930 | E9: Muxo | F9: 44 | G9: 90 | H9: 17 | I9: ? 2.50 | J9: 45691 | K9: 45391 | L9: 45693 | M9: 267 International Plaza | N9: 21 | O9: 91 | P9: Discontinued
A10: 66-268-8345 | B10: Greek Yogurt | C10: Dairy | D10: 32-182-1895 | E10: Thoughtstorm | F10: 91 | G10: 84 | H10: 11 | I10: ? 3.00 | J10: 45630 | K10: 45445 | L10: 45665 | M10: 550 Clemons Plaza | N10: 56 | O10: 90 | P10: Active
A11: 46-452-9419 | B11: Egg (Duck) | C11: Dairy | D11: 67-137-4215 | E11: Wordify | F11: 43 | G11: 10 | H11: 15 | I11: ? 1.00 | J11: 45614 | K11: 45610 | L11: 45481 | M11: 55782 Welch Hill | N11: 27 | O11: 69 | P11: Active
A12: 51-469-4611 | B12: Long Grain Rice | C12: Grains & Pulses | D12: 62-029-0827 | E12: Fivebridge | F12: 62 | G12: 81 | H12: 91 | I12: ? 1.60 | J12: 45644 | K12: 45436 | L12: 45664 | M12: 04776 Saint Paul Park | N12: 100 | O12: 42 | P12: Discontinued
A13: 42-220-9305 | B13: White Sugar | C13: Grains & Pulses | D13: 56-092-7992 | E13: Zooxo | F13: 91 | G13: 98 | H13: 6 | I13: ? 2.00 | J13: 45584 | K13: 45637 | L13: 45579 | M13: 61932 Cascade Crossing | N13: 100 | O13: 20 | P13: Backordered
... A991: 28-044-4102 | B991: Papaya | C991: Fruits & Vegetables | D991: 93-358-1118 | E991: Yakijo | F991: 19 | G991: 28 | H991: 83 | I991: ? 4.50 | J991: 45622 | K991: 45352 | L991: 45531 | M991: 309 Burning Wood Center | N991: 91 | O991: 73 | P991: Discontinued

Sheet Grocery and sales Data
A1: Product_ID | B1: Product_Name | C1: Category | D1: Supplier_ID | E1: Supplier_Name | F1: Stock_Quantity | G1: Reorder_Level | H1: Reorder_Quantity | I1: Unit_Price | J1: Total Stock Value | K1: Stock Status | L1: Reorder cost | M1: Received_Date | N1: Last_Order_Date | O1: Expiration_Date | P1: Warehouse_Location | Q1: Sales_Volume | R1: Revenue | S1: Inventory_Turnover_Rate | T1: Status | U1: Profit Margin
A2: 29-205-1132 | B2: Sushi Rice | C2: Grains & Pulses | D2: 38-037-1699 | E2: Jaxnation | F2: 22 | G2: 72 | H2: 70 | I2: 4.5 | J2: =I2*F2 -> 99 | K2: =IF(F2<=G2,"Low Stock_Reorder Needed","Stock_Sufficient") -> Low Stock_Reorder Needed | L2: =H2*I2 -> 315 | M2: 45520 | N2: 45472 | O2: 45554 | P2: 48 Del Sol Trail | Q2: 32 | R2: =Q2*I2 -> 144 | S2: 19 | T2: Discontinued | U2: =R2-J2 -> 45
A3: 40-681-9981 | B3: Arabica Coffee | C3: Beverages | D3: 54-470-2479 | E3: Feedmix | F3: 45 | G3: 77 | H3: 2 | I3: 20 | J3: =I3*F3 -> 900 | K3: =IF(F3<=G3,"Low Stock_Reorder Needed","Stock_Sufficient") -> Low Stock_Reorder Needed | L3: =H3*I3 -> 40 | M3: 45597 | N3: 45441 | O3: 45420 | P3: 36 3rd Place | Q3: 85 | R3: =Q3*I3 -> 1700 | S3: 1 | T3: Discontinued | U3: =R3-J3 -> 800
A4: 06-955-3428 | B4: Black Rice | C4: Grains & Pulses | D4: 54-031-2945 | E4: Vinder | F4: 30 | G4: 38 | H4: 83 | I4: 6 | J4: =I4*F4 -> 180 | K4: =IF(F4<=G4,"Low Stock_Reorder Needed","Stock_Sufficient") -> Low Stock_Reorder Needed | L4: =H4*I4 -> 498 | M4: 45507 | N4: 45453 | O4: 45557 | P4: 3296 Walton Court | Q4: 31 | R4: =Q4*I4 -> 186 | S4: 34 | T4: Backordered | U4: =R4-J4 -> 6
A5: 71-594-6552 | B5: Long Grain Rice | C5: Grains & Pulses | D5: 63-492-7603 | E5: Brightbean | F5: 12 | G5: 59 | H5: 62 | I5: 1.5 | J5: =I5*F5 -> 18 | K5: =IF(F5<=G5,"Low Stock_Reorder Needed","Stock_Sufficient") -> Low Stock_Reorder Needed | L5: =H5*I5 -> 93 | M5: 45634 | N5: 45707 | O5: 45399 | P5: 3 Westerfield Crossing | Q5: 95 | R5: =Q5*I5 -> 142.5 | S5: 99 | T5: Active | U5: =R5-J5 -> 124.5
A6: 57-437-1828 | B6: Plum | C6: Fruits & Vegetables | D6: 54-226-4308 | E6: Topicstorm | F6: 37 | G6: 30 | H6: 74 | I6: 4 | J6: =I6*F6 -> 148 | K6: =IF(F6<=G6,"Low Stock_Reorder Needed","Stock_Sufficient") -> Stock_Sufficient | L6: =H6*I6 -> 296 | M6: 45476 | N6: 45576 | O6: 45570 | P6: 15068 Scoville Court | Q6: 62 | R6: =Q6*I6 -> 248 | S6: 25 | T6: Backordered | U6: =R6-J6 -> 100
A7: 21-120-6238 | B7: All-Purpose Flour | C7: Grains & Pulses | D7: 86-292-4587 | E7: Dabjam | F7: 55 | G7: 33 | H7: 14 | I7: 1.75 | J7: =I7*F7 -> 96.25 | K7: =IF(F7<=G7,"Low Stock_Reorder Needed","Stock_Sufficient") -> Stock_Sufficient | L7: =H7*I7 -> 24.5 | M7: 45629 | N7: 45438 | O7: 45540 | P7: 050 Mcbride Avenue | Q7: 34 | R7: =Q7*I7 -> 59.5 | S7: 62 | T7: Discontinued | U7: =R7-J7 -> -36.75
A8: 71-516-1996 | B8: Corn Oil | C8: Oils & Fats | D8: 04-391-7610 | E8: Tagfeed | F8: 96 | G8: 52 | H8: 16 | I8: 2.5 | J8: =I8*F8 -> 240 | K8: =IF(F8<=G8,"Low Stock_Reorder Needed","Stock_Sufficient") -> Stock_Sufficient | L8: =H8*I8 -> 40 | M8: 45369 | N8: 45419 | O8: 45463 | P8: 12 Truax Court | Q8: 67 | R8: =Q8*I8 -> 167.5 | S8: 13 | T8: Active | U8: =R8-J8 -> -72.5
A9: 39-629-5554 | B9: Egg (Goose) | C9: Dairy | D9: 67-679-4930 | E9: Muxo | F9: 44 | G9: 90 | H9: 17 | I9: 2.5 | J9: =I9*F9 -> 110 | K9: =IF(F9<=G9,"Low Stock_Reorder Needed","Stock_Sufficient") -> Low Stock_Reorder Needed | L9: =H9*I9 -> 42.5 | M9: 45691 | N9: 45391 | O9: 45693 | P9: 267 International Plaza | Q9: 21 | R9: =Q9*I9 -> 52.5 | S9: 91 | T9: Discontinued | U9: =R9-J9 -> -57.5
A10: 66-268-8345 | B10: Greek Yogurt | C10: Dairy | D10: 32-182-1895 | E10: Thoughtstorm | F10: 91 | G10: 84 | H10: 11 | I10: 3 | J10: =I10*F10 -> 273 | K10: =IF(F10<=G10,"Low Stock_Reorder Needed","Stock_Sufficient") -> Stock_Sufficient | L10: =H10*I10 -> 33 | M10: 45630 | N10: 45445 | O10: 45665 | P10: 550 Clemons Plaza | Q10: 56 | R10: =Q10*I10 -> 168 | S10: 90 | T10: Active | U10: =R10-J10 -> -105
A11: 46-452-9419 | B11: Egg (Duck) | C11: Dairy | D11: 67-137-4215 | E11: Wordify | F11: 43 | G11: 10 | H11: 15 | I11: 1 | J11: =I11*F11 -> 43 | K11: =IF(F11<=G11,"Low Stock_Reorder Needed","Stock_Sufficient") -> Stock_Sufficient | L11: =H11*I11 -> 15 | M11: 45614 | N11: 45610 | O11: 45481 | P11: 55782 Welch Hill | Q11: 27 | R11: =Q11*I11 -> 27 | S11: 69 | T11: Active | U11: =R11-J11 -> -16
A12: 51-469-4611 | B12: Long Grain Rice | C12: Grains & Pulses | D12: 62-029-0827 | E12: Fivebridge | F12: 62 | G12: 81 | H12: 91 | I12: 1.6 | J12: =I12*F12 -> 99.2 | K12: =IF(F12<=G12,"Low Stock_Reorder Needed","Stock_Sufficient") -> Low Stock_Reorder Needed | L12: =H12*I12 -> 145.6 | M12: 45644 | N12: 45436 | O12: 45664 | P12: 04776 Saint Paul Park | Q12: 100 | R12: =Q12*I12 -> 160 | S12: 42 | T12: Discontinued | U12: =R12-J12 -> 60.8
A13: 42-220-9305 | B13: White Sugar | C13: Grains & Pulses | D13: 56-092-7992 | E13: Zooxo | F13: 91 | G13: 98 | H13: 6 | I13: 2 | J13: =I13*F13 -> 182 | K13: =IF(F13<=G13,"Low Stock_Reorder Needed","Stock_Sufficient") -> Low Stock_Reorder Needed | L13: =H13*I13 -> 12 | M13: 45584 | N13: 45637 | O13: 45579 | P13: 61932 Cascade Crossing | Q13: 100 | R13: =Q13*I13 -> 200 | S13: 20 | T13: Backordered | U13: =R13-J13 -> 18
... A991: 28-044-4102 | B991: Papaya | C991: Fruits & Vegetables | D991: 93-358-1118 | E991: Yakijo | F991: 19 | G991: 28 | H991: 83 | I991: 4.5 | J991: =I991*F991 -> 85.5 | K991: =IF(F991<=G991,"Low Stock_Reorder Needed","Stock_Sufficient") -> Low Stock_Reorder Needed | L991: =H991*I991 -> 373.5 | M991: 45622 | N991: 45352 | O991: 45531 | P991: 309 Burning Wood Center | Q991: 91 | R991: =Q991*I991 -> 409.5 | S991: 73 | T991: Discontinued | U991: =R991-J991 -> 324

Sheet Produc Details
A1: Product_ID | B1: Product Name | C1: Category | D1: Unit Price | E1: Revenue | F1: Price Category
A2: 29-205-1132 | B2: =_xlfn.XLOOKUP(A2,'Grocery and sales Data'!$A$1:$A$991,'Grocery and sales Data'!$B$1:$B$991) -> Sushi Rice | C2: =_xlfn.XLOOKUP(A2,'Grocery and sales Data'!$A$1:$A$991,'Grocery and sales Data'!$C$1:$C$991) -> Grains & Pulses | D2: =_xlfn.XLOOKUP(A2,'Grocery and sales Data'!$A$1:$A$991,'Grocery and sales Data'!$I$1:$I$991) -> 4.5 | E2: =_xlfn.XLOOKUP(A2,'Grocery and sales Data'!$A$1:$A$991,'Grocery and sales Data'!$R$1:$R$991) -> 144 | F2: =IF(E2>=1000,"High",IF(E2>=100,"Medium","Low")) -> Medium
A3: 40-681-9981 | B3: =_xlfn.XLOOKUP(A3,'Grocery and sales Data'!$A$1:$A$991,'Grocery and sales Data'!$B$1:$B$991) -> Arabica Coffee | C3: =_xlfn.XLOOKUP(A3,'Grocery and sales Data'!$A$1:$A$991,'Grocery and sales Data'!$C$1:$C$991) -> Beverages | D3: =_xlfn.XLOOKUP(A3,'Grocery and sales Data'!$A$1:$A$991,'Grocery and sales Data'!$I$1:$I$991) -> 20 | E3: =_xlfn.XLOOKUP(A3,'Grocery and sales Data'!$A$1:$A$991,'Grocery and sales Data'!$R$1:$R$991) -> 1700 | F3: =IF(E3>=1000,"High",IF(E3>=100,"Medium","Low")) -> High
A4: 06-955-3428 | B4: =_xlfn.XLOOKUP(A4,'Grocery and sales Data'!$A$1:$A$991,'Grocery and sales Data'!$B$1:$B$991) -> Black Rice | C4: =_xlfn.XLOOKUP(A4,'Grocery and sales Data'!$A$1:$A$991,'Grocery and sales Data'!$C$1:$C$991) -> Grains & Pulses | D4: =_xlfn.XLOOKUP(A4,'Grocery and sales Data'!$A$1:$A$991,'Grocery and sales Data'!$I$1:$I$991) -> 6 | E4: =_xlfn.XLOOKUP(A4,'Grocery and sales Data'!$A$1:$A$991,'Grocery and sales Data'!$R$1:$R$991) -> 186 | F4: =IF(E4>=1000,"High",IF(E4>=100,"Medium","Low")) -> Medium
A5: 71-594-6552 | B5: =_xlfn.XLOOKUP(A5,'Grocery and sales Data'!$A$1:$A$991,'Grocery and sales Data'!$B$1:$B$991) -> Long Grain Rice | C5: =_xlfn.XLOOKUP(A5,'Grocery and sales Data'!$A$1:$A$991,'Grocery and sales Data'!$C$1:$C$991) -> Grains & Pulses | D5: =_xlfn.XLOOKUP(A5,'Grocery and sales Data'!$A$1:$A$991,'Grocery and sales Data'!$I$1:$I$991) -> 1.5 | E5: =_xlfn.XLOOKUP(A5,'Grocery and sales Data'!$A$1:$A$991,'Grocery and sales Data'!$R$1:$R$991) -> 142.5 | F5: =IF(E5>=1000,"High",IF(E5>=100,"Medium","Low")) -> Medium
A6: 57-437-1828 | B6: =_xlfn.XLOOKUP(A6,'Grocery and sales Data'!$A$1:$A$991,'Grocery and sales Data'!$B$1:$B$991) -> Plum | C6: =_xlfn.XLOOKUP(A6,'Grocery and sales Data'!$A$1:$A$991,'Grocery and sales Data'!$C$1:$C$991) -> Fruits & Vegetables | D6: =_xlfn.XLOOKUP(A6,'Grocery and sales Data'!$A$1:$A$991,'Grocery and sales Data'!$I$1:$I$991) -> 4 | E6: =_xlfn.XLOOKUP(A6,'Grocery and sales Data'!$A$1:$A$991,'Grocery and sales Data'!$R$1:$R$991) -> 248 | F6: =IF(E6>=1000,"High",IF(E6>=100,"Medium","Low")) -> Medium
A7: 21-120-6238 | B7: =_xlfn.XLOOKUP(A7,'Grocery and sales Data'!$A$1:$A$991,'Grocery and sales Data'!$B$1:$B$991) -> All-Purpose Flour | C7: =_xlfn.XLOOKUP(A7,'Grocery and sales Data'!$A$1:$A$991,'Grocery and sales Data'!$C$1:$C$991) -> Grains & Pulses | D7: =_xlfn.XLOOKUP(A7,'Grocery and sales Data'!$A$1:$A$991,'Grocery and sales Data'!$I$1:$I$991) -> 1.75 | E7: =_xlfn.XLOOKUP(A7,'Grocery and sales Data'!$A$1:$A$991,'Grocery and sales Data'!$R$1:$R$991) -> 59.5 | F7: =IF(E7>=1000,"High",IF(E7>=100,"Medium","Low")) -> Low
A8: 71-516-1996 | B8: =_xlfn.XLOOKUP(A8,'Grocery and sales Data'!$A$1:$A$991,'Grocery and sales Data'!$B$1:$B$991) -> Corn Oil | C8: =_xlfn.XLOOKUP(A8,'Grocery and sales Data'!$A$1:$A$991,'Grocery and sales Data'!$C$1:$C$991) -> Oils & Fats | D8: =_xlfn.XLOOKUP(A8,'Grocery and sales Data'!$A$1:$A$991,'Grocery and sales Data'!$I$1:$I$991) -> 2.5 | E8: =_xlfn.XLOOKUP(A8,'Grocery and sales Data'!$A$1:$A$991,'Grocery and sales Data'!$R$1:$R$991) -> 167.5 | F8: =IF(E8>=1000,"High",IF(E8>=100,"Medium","Low")) -> Medium
A9: 39-629-5554 | B9: =_xlfn.XLOOKUP(A9,'Grocery and sales Data'!$A$1:$A$991,'Grocery and sales Data'!$B$1:$B$991) -> Egg (Goose) | C9: =_xlfn.XLOOKUP(A9,'Grocery and sales Data'!$A$1:$A$991,'Grocery and sales Data'!$C$1:$C$991) -> Dairy | D9: =_xlfn.XLOOKUP(A9,'Grocery and sales Data'!$A$1:$A$991,'Grocery and sales Data'!$I$1:$I$991) -> 2.5 | E9: =_xlfn.XLOOKUP(A9,'Grocery and sales Data'!$A$1:$A$991,'Grocery and sales Data'!$R$1:$R$991) -> 52.5 | F9: =IF(E9>=1000,"High",IF(E9>=100,"Medium","Low")) -> Low
A10: 66-268-8345 | B10: =_xlfn.XLOOKUP(A10,'Grocery and sales Data'!$A$1:$A$991,'Grocery and sales Data'!$B$1:$B$991) -> Greek Yogurt | C10: =_xlfn.XLOOKUP(A10,'Grocery and sales Data'!$A$1:$A$991,'Grocery and sales Data'!$C$1:$C$991) -> Dairy | D10: =_xlfn.XLOOKUP(A10,'Grocery and sales Data'!$A$1:$A$991,'Grocery and sales Data'!$I$1:$I$991) -> 3 | E10: =_xlfn.XLOOKUP(A10,'Grocery and sales Data'!$A$1:$A$991,'Grocery and sales Data'!$R$1:$R$991) -> 168 | F10: =IF(E10>=1000,"High",IF(E10>=100,"Medium","Low")) -> Medium
A11: 46-452-9419 | B11: =_xlfn.XLOOKUP(A11,'Grocery and sales Data'!$A$1:$A$991,'Grocery and sales Data'!$B$1:$B$991) -> Egg (Duck) | C11: =_xlfn.XLOOKUP(A11,'Grocery and sales Data'!$A$1:$A$991,'Grocery and sales Data'!$C$1:$C$991) -> Dairy | D11: =_xlfn.XLOOKUP(A11,'Grocery and sales Data'!$A$1:$A$991,'Grocery and sales Data'!$I$1:$I$991) -> 1 | E11: =_xlfn.XLOOKUP(A11,'Grocery and sales Data'!$A$1:$A$991,'Grocery and sales Data'!$R$1:$R$991) -> 27 | F11: =IF(E11>=1000,"High",IF(E11>=100,"Medium","Low")) -> Low
A12: 51-469-4611 | B12: =_xlfn.XLOOKUP(A12,'Grocery and sales Data'!$A$1:$A$991,'Grocery and sales Data'!$B$1:$B$991) -> Long Grain Rice | C12: =_xlfn.XLOOKUP(A12,'Grocery and sales Data'!$A$1:$A$991,'Grocery and sales Data'!$C$1:$C$991) -> Grains & Pulses | D12: =_xlfn.XLOOKUP(A12,'Grocery and sales Data'!$A$1:$A$991,'Grocery and sales Data'!$I$1:$I$991) -> 1.6 | E12: =_xlfn.XLOOKUP(A12,'Grocery and sales Data'!$A$1:$A$991,'Grocery and sales Data'!$R$1:$R$991) -> 160 | F12: =IF(E12>=1000,"High",IF(E12>=100,"Medium","Low")) -> Medium
A13: 42-220-9305 | B13: =_xlfn.XLOOKUP(A13,'Grocery and sales Data'!$A$1:$A$991,'Grocery and sales Data'!$B$1:$B$991) -> White Sugar | C13: =_xlfn.XLOOKUP(A13,'Grocery and sales Data'!$A$1:$A$991,'Grocery and sales Data'!$C$1:$C$991) -> Grains & Pulses | D13: =_xlfn.XLOOKUP(A13,'Grocery and sales Data'!$A$1:$A$991,'Grocery and sales Data'!$I$1:$I$991) -> 2 | E13: =_xlfn.XLOOKUP(A13,'Grocery and sales Data'!$A$1:$A$991,'Grocery and sales Data'!$R$1:$R$991) -> 200 | F13: =IF(E13>=1000,"High",IF(E13>=100,"Medium","Low")) -> Medium
... A991: 28-044-4102 | B991: =_xlfn.XLOOKUP(A991,'Grocery and sales Data'!$A$1:$A$991,'Grocery and sales Data'!$B$1:$B$991) -> Papaya | C991: =_xlfn.XLOOKUP(A991,'Grocery and sales Data'!$A$1:$A$991,'Grocery and sales Data'!$C$1:$C$991) -> Fruits & Vegetables | D991: =_xlfn.XLOOKUP(A991,'Grocery and sales Data'!$A$1:$A$991,'Grocery and sales Data'!$I$1:$I$991) -> 4.5 | E991: =_xlfn.XLOOKUP(A991,'Grocery and sales Data'!$A$1:$A$991,'Grocery and sales Data'!$R$1:$R$991) -> 409.5 | F991: =IF(E991>=1000,"High",IF(E991>=100,"Medium","Low")) -> Medium

Sheet Statistics
A1: Unit_Price | B1: Total Stock Value | C1: Reorder cost | D1: Revenue | E1: Profit Margin
A2: 4.5 | B2: 99 | C2: 315 | D2: 144 | E2: 45
A3: 20 | B3: 900 | C3: 40 | D3: 1700 | E3: 800
A4: 6 | B4: 180 | C4: 498 | D4: 186 | E4: 6 | G4: Unit_Price | I4: Total Stock Value | K4: Reorder cost | M4: Revenue | O4: Profit Margin
A5: 1.5 | B5: 18 | C5: 93 | D5: 142.5 | E5: 124.5
A6: 4 | B6: 148 | C6: 296 | D6: 248 | E6: 100 | G6: Mean | H6: 5.9241919 | I6: Mean | J6: 336.01486 | K6: Mean | L6: 308.57075 | M6: Mean | N6: 347.74681 | O6: Mean | P6: 11.731949
A7: 1.75 | B7: 96.25 | C7: 24.5 | D7: 59.5 | E7: -36.75 | G7: Standard Error | H7: 0.20630643 | I7: Standard Error | J7: 13.838639 | K7: Standard Error | L7: 13.803153 | M7: Standard Error | N7: 13.025277 | O7: Standard Error | P7: 8.4917043
A8: 2.5 | B8: 240 | C8: 40 | D8: 167.5 | E8: -72.5 | G8: Median | H8: 4.225 | I8: Median | J8: 209 | K8: Median | L8: 182.45 | M8: Median | N8: 231 | O8: Median | P8: 9
A9: 2.5 | B9: 110 | C9: 42.5 | D9: 52.5 | E9: -57.5 | G9: Mode | H9: 2.5 | I9: Mode | J9: 160 | K9: Mode | L9: 90 | M9: Mode | N9: 120 | O9: Mode | P9: 0
A10: 3 | B10: 273 | C10: 33 | D10: 168 | E10: -105 | G10: Standard Deviation | H10: 6.4912804 | I10: Standard Deviation | J10: 435.42262 | K10: Standard Deviation | L10: 434.30607 | M10: Standard Deviation | N10: 409.83079 | O10: Standard Deviation | P10: 267.18524
A11: 1 | B11: 43 | C11: 15 | D11: 27 | E11: -16 | G11: Sample Variance | H11: 42.136722 | I11: Sample Variance | J11: 189592.86 | K11: Sample Variance | L11: 188621.76 | M11: Sample Variance | N11: 167961.27 | O11: Sample Variance | P11: 71387.951
A12: 1.6 | B12: 99.2 | C12: 145.6 | D12: 160 | E12: 60.8 | G12: Kurtosis | H12: 55.967577 | I12: Kurtosis | J12: 46.970162 | K12: Kurtosis | L12: 50.307416 | M12: Kurtosis | N12: 32.727838 | O12: Kurtosis | P12: 13.684948
A13: 2 | B13: 182 | C13: 12 | D13: 200 | E13: 18 | G13: Skewness | H13: 5.5982512 | I13: Skewness | J13: 5.3524518 | K13: Skewness | L13: 5.5501779 | M13: Skewness | N13: 4.5062673 | O13: Skewness | P13: -0.75196741
A14: 3 | B14: 78 | C14: 93 | D14: 141 | E14: 63 | G14: Range | H14: 98.23 | I14: Range | J14: 5510.08 | K14: Range | L14: 5806.97 | M14: Range | N14: 4701.04 | O14: Range | P14: 3731.25
A15: 4 | B15: 380 | C15: 304 | D15: 276 | E15: -104 | G15: Minimum | H15: 0.2 | I15: Minimum | J15: 2 | K15: Minimum | L15: 0.4 | M15: Minimum | N15: 6.6 | O15: Minimum | P15: -2196.15
A16: 6 | B16: 324 | C16: 96 | D16: 378 | E16: 54 | G16: Maximum | H16: 98.43 | I16: Maximum | J16: 5512.08 | K16: Maximum | L16: 5807.37 | M16: Maximum | N16: 4707.64 | O16: Maximum | P16: 1535.1
A17: 7 | B17: 658 | C17: 105 | D17: 140 | E17: -518 | G17: Sum | H17: 5864.95 | I17: Sum | J17: 332654.71 | K17: Sum | L17: 305485.04 | M17: Sum | N17: 344269.34 | O17: Sum | P17: 11614.63
A18: 1.5 | B18: 40.5 | C18: 132 | D18: 99 | E18: 58.5 | G18: Count | H18: 990 | I18: Count | J18: 990 | K18: Count | L18: 990 | M18: Count | N18: 990 | O18: Count | P18: 990
A19: 8 | B19: 392 | C19: 208 | D19: 624 | E19: 232
A20: 20 | B20: 1100 | C20: 1680 | D20: 920 | E20: -180
A21: 2 | B21: 130 | C21: 164 | D21: 58 | E21: -72
A22: 2.5 | B22: 180 | C22: 247.5 | D22: 205 | E22: 25
A23: 12 | B23: 588 | C23: 576 | D23: 624 | E23: 36
A24: 2 | B24: 162 | C24: 56 | D24: 40 | E24: -122
A25: 1 | B25: 88 | C25: 55 | D25: 73 | E25: -15
A26: 12 | B26: 756 | C26: 1020 | D26: 708 | E26: -48
A27: 1.5 | B27: 46.5 | C27: 120 | D27: 69 | E27: 22.5
A28: 0.8 | B28: 77.6 | C28: 64.8 | D28: 77.6 | E28: 0
A29: 6 | B29: 432 | C29: 234 | D29: 564 | E29: 132
A30: 5 | B30: 80 | C30: 160 | D30: 250 | E30: 170
... A991: 4.5 | B991: 85.5 | C991: 373.5 | D991: 409.5 | E991: 324
